{
	"miniprogramRoot": "dist/",
	"projectname": "fe-taro-activity",
	"description": "taro-activity",
	"appid": "wx7f1d65332b8335a7",
	"setting": {
		"urlCheck": false,
		"es6": false,
		"postcss": false,
		"minified": false,
		"newFeature": true,
		"autoAudits": false,
		"checkInvalidKey": true,
		"checkSiteMap": true,
		"uploadWithSourceMap": true,
		"babelSetting": {
			"ignore": [],
			"disablePlugins": [],
			"outputPath": ""
		}
	},
	"compileType": "miniprogram",
	"simulatorType": "wechat",
	"simulatorPluginLibVersion": {},
	"condition": {}
}